app.py
db.py
db_init.py
models/__init__.py
models/film.py
models/film_shows.py
models/seat.py
models/show.py
models/theater.py
models/ticket.py
models/user.py
server_requests/__init__.py
server_requests/films.py
server_requests/login.py
server_requests/registration.py
server_requests/seats.py
server_requests/shows.py
server_requests/stats.py
server_requests/theatre.py
server_requests/tickets.py
server_requests/users.py
utils/__init__.py
utils/role_required_decorator.py
Flask_of_Cinema-1.0.0.dist-info/METADATA
Flask_of_Cinema-1.0.0.dist-info/WHEEL
Flask_of_Cinema-1.0.0.dist-info/top_level.txt
Flask_of_Cinema-1.0.0.dist-info/RECORD
