Metadata-Version: 2.1
Name: Flask-of-Cinema
Version: 1.0.0
Summary: A nice application. Really tho!
Home-page: https://gitlab.com/bicoccadisco/processo-e-sviluppo-del-software/2020_assignment1_flaskofcinema
Author: Alessandro Bernieri - 810104, Matteo Schizzerotto - 876362, Matteo Vergara - 874063
Author-email: UNKNOWN
License: MIT
Platform: UNKNOWN
Classifier: Development Status :: 4 - Beta
Classifier: Framework :: Flask
Classifier: Intended Audience :: Developers
Classifier: License :: OSI Approved :: MIT License
Classifier: Natural Language :: English
Classifier: Operating System :: OS Independent
Classifier: Programming Language :: Python
Classifier: Topic :: Education :: Testing
Requires-Dist: Flask
Requires-Dist: SQLAlchemyFlask-Loginpython-dotenvpsycopg2-binarywerkzeug
